cap_tools/__init__.py
cap_tools/models.py
cap_tools/py.typed
cap_tools/utils.py
cap_tools-3.1.1.dist-info/LICENSE
cap_tools-3.1.1.dist-info/METADATA
cap_tools-3.1.1.dist-info/WHEEL
cap_tools-3.1.1.dist-info/RECORD
