Metadata-Version: 2.1
Name: cap-tools
Version: 3.1.1
Summary: Python data bindings for the Common Alerting Protocol Version.
Home-page: https://github.com/bjoern-reetz/cap-tools
License: MIT
Keywords: cap,common alerting protocol,read,write,tool,util
Author: Björn Reetz
Author-email: git@bjoern-reetz.de
Requires-Python: >=3.10,<4.0
Classifier: Development Status :: 5 - Production/Stable
Classifier: Intended Audience :: Developers
Classifier: License :: OSI Approved :: MIT License
Classifier: Operating System :: OS Independent
Classifier: Programming Language :: Python :: 3
Classifier: Programming Language :: Python :: 3.10
Classifier: Programming Language :: Python :: 3.11
Classifier: Programming Language :: Python :: 3.12
Classifier: Topic :: Software Development :: Libraries :: Python Modules
Classifier: Topic :: Utilities
Classifier: Typing :: Typed
Requires-Dist: multidict (>=6.0.5,<7.0.0)
Requires-Dist: xsdata (>=24.4,<25.0)
Project-URL: Documentation, https://github.com/bjoern-reetz/cap-tools
Project-URL: Repository, https://github.com/bjoern-reetz/cap-tools
